proScatter-0.0.2.dist-info/entry_points.txt
proScatter-0.0.2.dist-info/metadata.json
proScatter-0.0.2.dist-info/METADATA
proScatter-0.0.2.dist-info/top_level.txt
proScatter-0.0.2.dist-info/RECORD
proScatter-0.0.2.dist-info/DESCRIPTION.rst
proScatter-0.0.2.dist-info/WHEEL
proscatter/xwalk2plink.py
proscatter/__init__.py
proscatter/readfasta.py
proscatter/parse.py
proscatter/proScatter.py
proscatter/loadfiles.py
proscatter/splotch.py
