Metadata-Version: 2.0
Name: proScatter
Version: 0.0.2
Summary: for visualizing pLink data from one or more experiments
Home-page: https://github.com/justinjee/proScatter
Author: Justin Jee
Author-email: justin.jee@gmail.com
License: MIT
Platform: UNKNOWN
Classifier: Intended Audience :: Science/Research
Classifier: Programming Language :: Python
Classifier: Topic :: Scientific/Engineering :: Bio-Informatics
Classifier: Topic :: Scientific/Engineering :: Visualization
Classifier: Operating System :: Microsoft :: Windows
Classifier: Operating System :: POSIX
Classifier: Operating System :: Unix
Classifier: Operating System :: MacOS
Classifier: Programming Language :: Python :: 2
Classifier: Programming Language :: Python :: 2.7
Classifier: Programming Language :: Python :: 3
Classifier: Programming Language :: Python :: 3.3
Requires-Dist: bokeh
Requires-Dist: pandas (>=0.16.0)
Requires-Dist: numpy
